Metadata-Version: 2.1
Name: latestearthquake-indonesia-v.1
Version: 0.9
Summary: This package will get the latest earthquake from BMKG | Meteorological, Climatological, and Geophysical Agency
Home-page: https://github.com/nurarif151/latest-indonesia-earthquake
Author: Nur Arif
Author-email: nurarif0151@gmail.com
Project-URL: Website, https://teollo.id
Classifier: Programming Language :: Python :: 3
Classifier: License :: OSI Approved :: GNU General Public License v3 (GPLv3)
Classifier: Operating System :: OS Independent
Classifier: Development Status :: 5 - Production/Stable
Requires-Python: >=3.6
License-File: LICENSE
